{"timestamp": "2021-10-30T15:42:20.456275", "dir_name": "/data/degrigis/HB_FW_DATASET/nordic/app.bin@9486833bbe2529337ba95e7ec5c24c89", "blob_name": "app.bin@9486833bbe2529337ba95e7ec5c24c89", "hb_folder": "/data/degrigis/HB_FW_DATASET/nordic/app.bin@9486833bbe2529337ba95e7ec5c24c89/hb_analysis", "blob_project": "/data/degrigis/HB_FW_DATASET/nordic/app.bin@9486833bbe2529337ba95e7ec5c24c89/hb_analysis/app.bin@9486833bbe2529337ba95e7ec5c24c89.proj", "base_address": 114688, "blob_entry_point": "0x1c339", "blob_stack_pointer": "0x2000b580", "num_of_functions": 599, "bf_candidates": [{"name": "IdentifiableMemcpy", "pointer_regs": ["r0", "r1"], "addr": [115713]}, {"name": "IdentifiableReverseMemcpy", "pointer_regs": [], "addr": []}, {"name": "IdentifiableMemset", "pointer_regs": [], "addr": []}, {"name": "IdentifiableReverseMemset", "pointer_regs": ["r0"], "addr": [115777]}, {"name": "IdentifiableMemcmp", "pointer_regs": [], "addr": []}, {"name": "IdentifiableStrlen", "pointer_regs": ["r0"], "addr": [115813]}, {"name": "IdentifiableStrncat", "pointer_regs": [], "addr": []}, {"name": "IdentifiableStrcat", "pointer_regs": [], "addr": []}, {"name": "IdentifiableStrncpy", "pointer_regs": [], "addr": []}], "find_bf_timestamp": "2021-10-30T16:09:25.912443", "identify_pointers_timestamp": "2021-10-30T16:12:55.780868", "pointer_sources": ["0x219cd", "0x1c465", "0x2ebed", "0x25cad"], "calls_analyzed": ["0x219cd", "0x1c465", "0x2ebed", "0x25cad"], "caller_analyzed": ["0x1d681", "0x2a101", "0x2c309", "0x2600d", "0x21a11", "0x22411", "0x2a415", "0x25b19", "0x268a5", "0x2a8f9", "0x22aa5", "0x2b0a9", "0x22bb5", "0x1da39", "0x203bd", "0x29d3d", "0x27bc1", "0x222cd", "0x1c44f", "0x204d1", "0x23dd1", "0x1c453", "0x24155", "0x294d9", "0x25ae1", "0x1fc61", "0x23ce1", "0x1d069", "0x21ee9", "0x2be71", "0x249f5", "0x2b5f5", "0x21a79", "0x247fd"], "discovery_contributions": {"IdentifiableMemcpy": ["0x1c465", "0x2ebed"], "IdentifiableReverseMemcpy": [], "IdentifiableMemset": [], "IdentifiableReverseMemset": [], "IdentifiableMemcmp": [], "IdentifiableStrlen": ["0x219cd", "0x25cad"], "IdentifiableStrncat": [], "IdentifiableStrcat": [], "IdentifiableStrncpy": []}, "working_pointer_sources": [], "tot_num_instructions_disassembled": 24222}