{"timestamp": "2021-10-29T09:43:15.660977", "dir_name": "/data/degrigis/HB_FW_DATASET/nordic/ble_app_lampe_32k.bin@686f1c94c4a7fb57a4aa9b114aeea0a4", "blob_name": "ble_app_lampe_32k.bin@686f1c94c4a7fb57a4aa9b114aeea0a4", "hb_folder": "/data/degrigis/HB_FW_DATASET/nordic/ble_app_lampe_32k.bin@686f1c94c4a7fb57a4aa9b114aeea0a4/hb_analysis", "blob_project": "/data/degrigis/HB_FW_DATASET/nordic/ble_app_lampe_32k.bin@686f1c94c4a7fb57a4aa9b114aeea0a4/hb_analysis/ble_app_lampe_32k.bin@686f1c94c4a7fb57a4aa9b114aeea0a4.proj", "base_address": 98304, "blob_entry_point": "0x1de39", "blob_stack_pointer": "0x200048f8", "num_of_functions": 455, "bf_candidates": [{"name": "IdentifiableMemcpy", "pointer_regs": ["r0", "r1"], "addr": [140229]}, {"name": "IdentifiableReverseMemcpy", "pointer_regs": [], "addr": []}, {"name": "IdentifiableMemset", "pointer_regs": [], "addr": []}, {"name": "IdentifiableReverseMemset", "pointer_regs": ["r0"], "addr": [140265]}, {"name": "IdentifiableMemcmp", "pointer_regs": [], "addr": []}, {"name": "IdentifiableStrlen", "pointer_regs": ["r0"], "addr": [140301]}, {"name": "IdentifiableStrncat", "pointer_regs": [], "addr": []}, {"name": "IdentifiableStrcat", "pointer_regs": [], "addr": []}, {"name": "IdentifiableStrncpy", "pointer_regs": [], "addr": []}], "find_bf_timestamp": "2021-10-29T10:32:25.006153", "identify_pointers_timestamp": "2021-10-29T10:33:56.555588", "pointer_sources": ["0x1fe29"], "calls_analyzed": ["0x1fe29"], "caller_analyzed": ["0x1bf81", "0x215f7", "0x1fc85", "0x20c8d", "0x20a8d", "0x21499", "0x18619", "0x1ff1b", "0x21c19", "0x1a49b", "0x21c9f", "0x211a1", "0x217a5", "0x1a027", "0x1aca9", "0x1c62b", "0x1c6ab", "0x20aab", "0x204af", "0x21caf", "0x1f631", "0x1adb1", "0x18bb3", "0x1c133", "0x1dc2f", "0x1e0b3", "0x1c2bb", "0x2123d", "0x1c443", "0x20fc9", "0x1fdcf", "0x1dbd7", "0x20559", "0x205df", "0x1a461", "0x217e3", "0x1dce3", "0x21c65", "0x1d865", "0x1a26b", "0x20bef", "0x1e271", "0x21673", "0x223f7", "0x1dc75", "0x1c275", "0x18577", "0x223fb", "0x1fffd", "0x1ff7f"], "discovery_contributions": {"IdentifiableMemcpy": ["0x1fe29"], "IdentifiableReverseMemcpy": [], "IdentifiableMemset": [], "IdentifiableReverseMemset": [], "IdentifiableMemcmp": [], "IdentifiableStrlen": [], "IdentifiableStrncat": [], "IdentifiableStrcat": [], "IdentifiableStrncpy": []}, "working_pointer_sources": [], "tot_num_instructions_disassembled": 19303}