{"timestamp": "2021-10-23T23:19:53.021738", "dir_name": "/data/degrigis/HB_FW_DATASET/nordic/L38I.bin@0fcad621bfca6b1ade9667c7a23433dc", "blob_name": "L38I.bin@0fcad621bfca6b1ade9667c7a23433dc", "hb_folder": "/data/degrigis/HB_FW_DATASET/nordic/L38I.bin@0fcad621bfca6b1ade9667c7a23433dc/hb_analysis", "blob_project": "/data/degrigis/HB_FW_DATASET/nordic/L38I.bin@0fcad621bfca6b1ade9667c7a23433dc/hb_analysis/L38I.bin@0fcad621bfca6b1ade9667c7a23433dc.proj", "base_address": 98304, "blob_entry_point": "0x18255", "blob_stack_pointer": "0x20006c38", "num_of_functions": 1176, "bf_candidates": [{"name": "IdentifiableMemcpy", "pointer_regs": ["r0", "r1"], "addr": [117957, 208971]}, {"name": "IdentifiableReverseMemcpy", "pointer_regs": [], "addr": []}, {"name": "IdentifiableMemset", "pointer_regs": [], "addr": []}, {"name": "IdentifiableReverseMemset", "pointer_regs": ["r0"], "addr": [118021]}, {"name": "IdentifiableMemcmp", "pointer_regs": [], "addr": []}, {"name": "IdentifiableStrlen", "pointer_regs": ["r0"], "addr": [118057]}, {"name": "IdentifiableStrncat", "pointer_regs": [], "addr": []}, {"name": "IdentifiableStrcat", "pointer_regs": [], "addr": []}, {"name": "IdentifiableStrncpy", "pointer_regs": [], "addr": []}], "find_bf_timestamp": "2021-10-24T00:56:07.778336", "identify_pointers_timestamp": "2021-10-24T01:00:14.978251", "pointer_sources": ["0x1de25", "0x31c85", "0x20609", "0x1cd29", "0x3578d", "0x20cd5", "0x33295", "0x353dd"], "calls_analyzed": ["0x1de25", "0x31c85", "0x20609", "0x1cd29", "0x3578d", "0x20cd5", "0x33295", "0x353dd"], "caller_analyzed": ["0x1ed81", "0x31b83", "0x21e05", "0x33f89", "0x1d509", "0x3068d", "0x26e0d", "0x1840d", "0x20391", "0x26a11", "0x1cd13", "0x2f715", "0x30695", "0x1e815", "0x1cd17", "0x2d419", "0x23399", "0x2db1d", "0x2bd21", "0x25b25", "0x305a9", "0x2c1a9", "0x2da29", "0x2cb2f", "0x30e31", "0x27031", "0x2c0b1", "0x33bb1", "0x2b135", "0x32d35", "0x26a35", "0x2f7b1", "0x2ddb9", "0x2bab9", "0x2c139", "0x2a8b3", "0x34b3d", "0x2f8bd", "0x2fac1", "0x2f2c1", "0x286c1", "0x30145", "0x1f345", "0x2bc47", "0x1ea49", "0x1d249", "0x18549", "0x32ac9", "0x2e04d", "0x31dd1", "0x2ba53", "0x2d9d5", "0x2bed5", "0x1d1d5", "0x32b57", "0x305d9", "0x26ad9", "0x27ed9", "0x3305b", "0x2ebdd", "0x2f7dd", "0x20ce1", "0x182e1", "0x30ae5", "0x26d65", "0x26e65", "0x32c69", "0x1fce9", "0x2e1f9", "0x27d6f", "0x2c071", "0x27f71", "0x21ff1", "0x2d475", "0x2dff5", "0x18677", "0x27e75", "0x2c0f9"], "discovery_contributions": {"IdentifiableMemcpy": ["0x1de25", "0x20609", "0x1cd29", "0x3578d", "0x20cd5", "0x353dd"], "IdentifiableReverseMemcpy": [], "IdentifiableMemset": [], "IdentifiableReverseMemset": ["0x33295", "0x31c85"], "IdentifiableMemcmp": [], "IdentifiableStrlen": ["0x1cd29"], "IdentifiableStrncat": [], "IdentifiableStrcat": [], "IdentifiableStrncpy": []}, "tot_num_instructions_disassembled": 49017}