{"timestamp": "2021-10-30T18:00:11.851126", "dir_name": "/data/degrigis/HB_FW_DATASET/nordic/application_r4.bin@892b3fe6f1c08adfe0f8001324701cd9", "blob_name": "application_r4.bin@892b3fe6f1c08adfe0f8001324701cd9", "hb_folder": "/data/degrigis/HB_FW_DATASET/nordic/application_r4.bin@892b3fe6f1c08adfe0f8001324701cd9/hb_analysis", "blob_project": "/data/degrigis/HB_FW_DATASET/nordic/application_r4.bin@892b3fe6f1c08adfe0f8001324701cd9/hb_analysis/application_r4.bin@892b3fe6f1c08adfe0f8001324701cd9.proj", "base_address": 114688, "blob_entry_point": "0x1c3b1", "blob_stack_pointer": "0x2000d470", "num_of_functions": 611, "bf_candidates": [{"name": "IdentifiableMemcpy", "pointer_regs": ["r0", "r1"], "addr": [139773]}, {"name": "IdentifiableReverseMemcpy", "pointer_regs": [], "addr": []}, {"name": "IdentifiableMemset", "pointer_regs": [], "addr": []}, {"name": "IdentifiableReverseMemset", "pointer_regs": ["r0"], "addr": [139837]}, {"name": "IdentifiableMemcmp", "pointer_regs": [], "addr": []}, {"name": "IdentifiableStrlen", "pointer_regs": ["r0"], "addr": [139873]}, {"name": "IdentifiableStrncat", "pointer_regs": [], "addr": []}, {"name": "IdentifiableStrcat", "pointer_regs": [], "addr": []}, {"name": "IdentifiableStrncpy", "pointer_regs": [], "addr": []}], "find_bf_timestamp": "2021-10-30T18:59:01.792360", "identify_pointers_timestamp": "2021-10-30T19:02:33.101820", "pointer_sources": ["0x2d781"], "calls_analyzed": ["0x2d781"], "caller_analyzed": ["0x25441", "0x27079", "0x34d03", "0x1f3e5", "0x1f389", "0x2224b", "0x30ead", "0x2224f", "0x329b1", "0x205d1", "0x2b271", "0x207f5", "0x2b235", "0x205f7", "0x2dbd5", "0x2ec37", "0x2ed9d"], "discovery_contributions": {"IdentifiableMemcpy": ["0x2d781"], "IdentifiableReverseMemcpy": [], "IdentifiableMemset": [], "IdentifiableReverseMemset": [], "IdentifiableMemcmp": [], "IdentifiableStrlen": [], "IdentifiableStrncat": [], "IdentifiableStrcat": [], "IdentifiableStrncpy": []}, "working_pointer_sources": [{"ps_addr": 186241, "ps_ct": {"r0": 8}, "hi_addr": 115633, "dump_name": "/data/degrigis/HB_FW_DATASET/nordic/application_r4.bin@892b3fe6f1c08adfe0f8001324701cd9/hb_analysis/0x2d781_0x1c3b1_mem_dump.mem", "needs_unpacked_data": true}], "best_hml_pairs": [{"malloc": "0x2d781", "free": "0x28b81", "hi": "0x1c3b1", "mem_dump_path": "/data/degrigis/HB_FW_DATASET/nordic/application_r4.bin@892b3fe6f1c08adfe0f8001324701cd9/hb_analysis/0x2d781_0x1c3b1_mem_dump.mem", "malloc_ct": {"r0": 8}, "free_ct": {"r0": "TOP"}}], "final_allocator": {"malloc": "0x2d781", "free": "0x28b81", "hi": "0x1c3b1", "mem_dump_path": "/data/degrigis/HB_FW_DATASET/nordic/application_r4.bin@892b3fe6f1c08adfe0f8001324701cd9/hb_analysis/0x2d781_0x1c3b1_mem_dump.mem", "malloc_ct": {"r0": 8}, "free_ct": {"r0": "TOP"}}, "malloc_prototype": "{\"ret\": \"r0\", \"arg_0\": \"size\"}", "malloc_prototype_string": "\"unsigned int * malloc(int size)\"", "free_prototype": "{\"arg_0\": \"ptr_to_free\"}", "free_prototype_string": "\"void free(unsigned int * arg_0)\"", "malloc_call": "malloc(malloc_sizes[{}])", "free_call": "free(ctrl_data_{}.global_var)", "fake_free_call": "free(((uint8_t *) &sym_data.data) + mem2chunk_offset)", "double_free_call": "free(ctrl_data_{}.global_var)", "malloc_unknown_arguments": 0, "malloc_unknown_arguments_vals": {}, "free_unknown_arguments": 0, "free_unknown_arguments_vals": {}, "malloc_to_hook_funcs": [], "free_to_hook_funcs": [], "heap_base": 536908912, "heap_grow_direction": ">", "mem2chunk_offset": 4, "header_size": 4, "allocator_works": 1, "threat_properties": ["MALLOC_XREFS: 4", "MMIO_MALLOC", "MMIO_FREE", "MMIO_MALLOC_0x28085_VARIABLE_SIZE_TO_BF_CODELOC_0x2edbb"], "tot_num_instructions_disassembled": 25595}