{"timestamp": "2021-11-02T22:05:43.617479", "dir_name": "/data/degrigis/HB_FW_DATASET/nordic/application.bin@b5c007023cbd0ebd0b44408aee49a7f6", "blob_name": "application.bin@b5c007023cbd0ebd0b44408aee49a7f6", "hb_folder": "/data/degrigis/HB_FW_DATASET/nordic/application.bin@b5c007023cbd0ebd0b44408aee49a7f6/hb_analysis", "blob_project": "/data/degrigis/HB_FW_DATASET/nordic/application.bin@b5c007023cbd0ebd0b44408aee49a7f6/hb_analysis/application.bin@b5c007023cbd0ebd0b44408aee49a7f6.proj", "base_address": 159744, "blob_entry_point": "0x27505", "blob_stack_pointer": "0x2000b958", "num_of_functions": 705, "bf_candidates": [{"name": "IdentifiableMemcpy", "pointer_regs": ["r0", "r1"], "addr": [161065]}, {"name": "IdentifiableReverseMemcpy", "pointer_regs": [], "addr": []}, {"name": "IdentifiableMemset", "pointer_regs": [], "addr": []}, {"name": "IdentifiableReverseMemset", "pointer_regs": ["r0"], "addr": [161129]}, {"name": "IdentifiableMemcmp", "pointer_regs": [], "addr": []}, {"name": "IdentifiableStrlen", "pointer_regs": ["r0"], "addr": [161201]}, {"name": "IdentifiableStrncat", "pointer_regs": [], "addr": []}, {"name": "IdentifiableStrcat", "pointer_regs": [], "addr": []}, {"name": "IdentifiableStrncpy", "pointer_regs": [], "addr": []}], "find_bf_timestamp": "2021-11-02T22:25:42.402332", "identify_pointers_timestamp": "2021-11-02T22:58:48.750606", "pointer_sources": ["0x2a085", "0x2758d", "0x275b1", "0x2a055", "0x3f93d"], "calls_analyzed": ["0x2a085", "0x2758d", "0x275b1", "0x2a055", "0x3f93d"], "caller_analyzed": ["0x2e381", "0x2ed81", "0x3c703", "0x2ec81", "0x2b381", "0x29709", "0x2ef89", "0x2e30d", "0x28f15", "0x2fc99", "0x2b029", "0x32b29", "0x3cb29", "0x39d2d", "0x32e2d", "0x3c235", "0x37db5", "0x33835", "0x2b2b5", "0x3e5b9", "0x31b3f", "0x32741", "0x3bd45", "0x2fe49", "0x2e8c9", "0x32a4d", "0x2b0cd", "0x2e34d", "0x3b751", "0x28ed1", "0x2b151", "0x3dcd5", "0x33955", "0x2e2d5", "0x32fdd", "0x330e1", "0x336e1", "0x3d965", "0x3c969", "0x29c6d", "0x2fdef", "0x34671", "0x2b077", "0x2757b", "0x28bfd", "0x27577"], "discovery_contributions": {"IdentifiableMemcpy": ["0x2a085", "0x2758d", "0x275b1", "0x2a055", "0x3f93d"], "IdentifiableReverseMemcpy": [], "IdentifiableMemset": [], "IdentifiableReverseMemset": [], "IdentifiableMemcmp": [], "IdentifiableStrlen": [], "IdentifiableStrncat": [], "IdentifiableStrcat": [], "IdentifiableStrncpy": []}, "working_pointer_sources": [], "tot_num_instructions_disassembled": 30902}