{"timestamp": "2021-11-08T23:47:52.520402", "dir_name": "/data/degrigis/HB_FW_DATASET/fitbit/flex_7_81_flash.bin", "blob_name": "flex_7_81_flash.bin", "hb_folder": "/data/degrigis/HB_FW_DATASET/fitbit/flex_7_81_flash.bin/hb_analysis", "blob_project": "/data/degrigis/HB_FW_DATASET/fitbit/flex_7_81_flash.bin/hb_analysis/flex_7_81_flash.bin.proj", "base_address": 0, "blob_entry_point": "0x83", "blob_stack_pointer": "0x20000080", "num_of_functions": 1423, "bf_candidates": [{"name": "IdentifiableMemcpy", "pointer_regs": ["r0", "r1"], "addr": [7525, 7557, 23203, 63425, 63457, 101509, 103045]}, {"name": "IdentifiableReverseMemcpy", "pointer_regs": [], "addr": []}, {"name": "IdentifiableMemset", "pointer_regs": [], "addr": []}, {"name": "IdentifiableReverseMemset", "pointer_regs": ["r0"], "addr": [71537]}, {"name": "IdentifiableMemcmp", "pointer_regs": [], "addr": []}, {"name": "IdentifiableStrlen", "pointer_regs": ["r0"], "addr": [127209]}, {"name": "IdentifiableStrncat", "pointer_regs": [], "addr": []}, {"name": "IdentifiableStrcat", "pointer_regs": [], "addr": []}, {"name": "IdentifiableStrncpy", "pointer_regs": [], "addr": []}], "find_bf_timestamp": "2021-11-09T00:46:20.441565", "identify_pointers_timestamp": "2021-11-09T01:01:53.100114", "pointer_sources": ["0x1ecfd", "0xd7c3", "0xd6c7", "0x1f0e9", "0x3b4b", "0x4d77", "0x1f0d1", "0xe133", "0xfdb7", "0xd9d9", "0x36dd", "0x36df"], "calls_analyzed": ["0x1ecfd", "0xd7c3", "0xd6c7", "0x1f0e9", "0x3b4b", "0x4d77", "0x1f0d1", "0xe133", "0xfdb7", "0xd9d9", "0x36dd", "0x36df"], "caller_analyzed": ["0x1403", "0xb60b", "0x5a11", "0x813", "0x19019", "0x10021", "0xe623", "0x3c27", "0x11027", "0xe231", "0x2243", "0xaa43", "0xec45", "0xf049", "0xe64b", "0xc64d", "0xee4d", "0xfe4f", "0xf255", "0xb655", "0xa259", "0x365d", "0x5863", "0x1246d", "0x15c6d", "0xee77", "0x1227b", "0x287d", "0x1907f", "0x12c81", "0xa283", "0x18c85", "0x1a87", "0x1c89", "0x19093", "0xa293", "0x2297", "0xa699", "0xb4a1", "0xfea3", "0xb6a5", "0xeeb3", "0xe2b3", "0x11cb5", "0xceb5", "0x1cb9", "0xecc5", "0x102c9", "0x108c9", "0xcecd", "0x36cf", "0xa8d9", "0xe8db", "0x10edd", "0xee3", "0x1eee7", "0x4cf1", "0x1af7", "0x34f7", "0x22f9", "0x5905", "0xe307", "0x5911", "0x11311", "0x21b17", "0xef1f", "0x2b21", "0xe123", "0xe133", "0x253f", "0xcb4d", "0x19151", "0x759", "0xb75b", "0x11761", "0x22d61", "0xe369", "0xd71", "0xb771", "0xf579", "0xbd79", "0xd7f", "0x10791", "0x2795", "0x19195", "0xa997", "0x15b99", "0xe59d", "0xff9f", "0x59a3", "0x18fa3", "0x191b9", "0x1fbb", "0x2bbd", "0x21c1", "0xd7c3", "0xabc3", "0x25c5", "0x59d1", "0xb5d5", "0xb7d9", "0xd9d9", "0x1bdb", "0x11fe7", "0x191e7", "0x25ed", "0xff1", "0xe7f3", "0x5f5"], "discovery_contributions": {"IdentifiableMemcpy": ["0xd7c3", "0xd6c7", "0x3b4b", "0x4d77", "0xe133", "0xfdb7", "0xd9d9", "0x36dd", "0x36df"], "IdentifiableReverseMemcpy": [], "IdentifiableMemset": [], "IdentifiableReverseMemset": [], "IdentifiableMemcmp": [], "IdentifiableStrlen": ["0x1f0e9", "0x1f0d1", "0x1ecfd"], "IdentifiableStrncat": [], "IdentifiableStrcat": [], "IdentifiableStrncpy": []}, "working_pointer_sources": [], "tot_num_instructions_disassembled": 50072}