{"timestamp": "2021-10-22T23:29:33.157823", "dir_name": "/data/degrigis/HB_FW_DATASET/nordic/mudra-capsule-v12.bin@aedec5b8393442405cdefb0bce140487", "blob_name": "mudra-capsule-v12.bin@aedec5b8393442405cdefb0bce140487", "hb_folder": "/data/degrigis/HB_FW_DATASET/nordic/mudra-capsule-v12.bin@aedec5b8393442405cdefb0bce140487/hb_analysis", "blob_project": "/data/degrigis/HB_FW_DATASET/nordic/mudra-capsule-v12.bin@aedec5b8393442405cdefb0bce140487/hb_analysis/mudra-capsule-v12.bin@aedec5b8393442405cdefb0bce140487.proj", "base_address": 155648, "blob_entry_point": "0x34f99", "blob_stack_pointer": "0x20010000", "num_of_functions": 1260, "bf_candidates": [{"name": "IdentifiableMemcpy", "pointer_regs": ["r0", "r1"], "addr": [256097, 287631, 287653]}, {"name": "IdentifiableReverseMemcpy", "pointer_regs": [], "addr": []}, {"name": "IdentifiableMemset", "pointer_regs": ["r0"], "addr": [287705]}, {"name": "IdentifiableReverseMemset", "pointer_regs": [], "addr": []}, {"name": "IdentifiableMemcmp", "pointer_regs": [], "addr": []}, {"name": "IdentifiableStrlen", "pointer_regs": ["r0"], "addr": [287721]}, {"name": "IdentifiableStrncat", "pointer_regs": [], "addr": []}, {"name": "IdentifiableStrcat", "pointer_regs": [], "addr": []}, {"name": "IdentifiableStrncpy", "pointer_regs": [], "addr": []}], "find_bf_timestamp": "2021-10-22T23:46:32.189417", "identify_pointers_timestamp": "2021-10-22T23:54:46.662453", "pointer_sources": ["0x2d81b", "0x3de13"], "calls_analyzed": ["0x2d81b", "0x3de13"], "caller_analyzed": ["0x3e901", "0x2f081", "0x32a03", "0x3e985", "0x34a05", "0x2e309", "0x2dc89", "0x36499", "0x3b919", "0x36199", "0x36399", "0x3e49f", "0x376a1", "0x3f7a3", "0x34ea5", "0x3ae27", "0x3fcad", "0x3e92d", "0x3282d", "0x3692f", "0x3f6b1", "0x3b8b3", "0x31e35", "0x3e835", "0x43535", "0x367bb", "0x3ec3b", "0x3e7c1", "0x369fd", "0x3f741", "0x3ef45", "0x278c9", "0x38bc9", "0x2ee49", "0x2e8cb", "0x348cd", "0x3fdf9", "0x3bad5", "0x364d5", "0x29255", "0x3e8d5", "0x3f9d5", "0x3e959", "0x2ec5b", "0x365dd", "0x2e4e5", "0x34865", "0x2e3e7", "0x43669", "0x3bbf1", "0x3ab71", "0x36873", "0x3f2f3", "0x2e875", "0x3faf9", "0x313f9"], "discovery_contributions": {"IdentifiableMemcpy": ["0x3de13"], "IdentifiableReverseMemcpy": [], "IdentifiableMemset": ["0x2d81b"], "IdentifiableReverseMemset": [], "IdentifiableMemcmp": [], "IdentifiableStrlen": [], "IdentifiableStrncat": [], "IdentifiableStrcat": [], "IdentifiableStrncpy": []}, "working_pointer_sources": [], "tot_num_instructions_disassembled": 55349}