{"timestamp": "2021-10-29T07:51:08.054281", "dir_name": "/data/degrigis/HB_FW_DATASET/nordic/bootloader.bin@b13d150372a2102653a8fddf58c62f8f", "blob_name": "bootloader.bin@b13d150372a2102653a8fddf58c62f8f", "hb_folder": "/data/degrigis/HB_FW_DATASET/nordic/bootloader.bin@b13d150372a2102653a8fddf58c62f8f/hb_analysis", "blob_project": "/data/degrigis/HB_FW_DATASET/nordic/bootloader.bin@b13d150372a2102653a8fddf58c62f8f/hb_analysis/bootloader.bin@b13d150372a2102653a8fddf58c62f8f.proj", "base_address": 245760, "blob_entry_point": "0x3c4e9", "blob_stack_pointer": "0x20003c40", "num_of_functions": 173, "bf_candidates": [{"name": "IdentifiableMemcpy", "pointer_regs": ["r0", "r1"], "addr": [258193]}, {"name": "IdentifiableReverseMemcpy", "pointer_regs": [], "addr": []}, {"name": "IdentifiableMemset", "pointer_regs": [], "addr": []}, {"name": "IdentifiableReverseMemset", "pointer_regs": ["r0"], "addr": [258229]}, {"name": "IdentifiableMemcmp", "pointer_regs": [], "addr": []}, {"name": "IdentifiableStrlen", "pointer_regs": ["r0"], "addr": [258265]}, {"name": "IdentifiableStrncat", "pointer_regs": [], "addr": []}, {"name": "IdentifiableStrcat", "pointer_regs": [], "addr": []}, {"name": "IdentifiableStrncpy", "pointer_regs": [], "addr": []}], "find_bf_timestamp": "2021-10-29T08:14:28.635187", "identify_pointers_timestamp": "2021-10-29T08:14:51.914161", "pointer_sources": ["0x3c825"], "calls_analyzed": ["0x3c825"], "caller_analyzed": ["0x3c681", "0x3f0c3", "0x3c1c5", "0x3eca7", "0x3f0c7", "0x3e0eb", "0x3c7cb", "0x3c16d", "0x3e54d", "0x3ca4f", "0x3dfb1", "0x3c917", "0x3d359", "0x3c97b", "0x3cafd"], "discovery_contributions": {"IdentifiableMemcpy": ["0x3c825"], "IdentifiableReverseMemcpy": [], "IdentifiableMemset": [], "IdentifiableReverseMemset": [], "IdentifiableMemcmp": [], "IdentifiableStrlen": [], "IdentifiableStrncat": [], "IdentifiableStrcat": [], "IdentifiableStrncpy": []}, "working_pointer_sources": [], "tot_num_instructions_disassembled": 6094}